lumberjax/__init__.py
lumberjax/cli.py
lumberjax/lumberjax.py
lumberjax-0.1.0.dist-info/AUTHORS.rst
lumberjax-0.1.0.dist-info/LICENSE
lumberjax-0.1.0.dist-info/METADATA
lumberjax-0.1.0.dist-info/WHEEL
lumberjax-0.1.0.dist-info/entry_points.txt
lumberjax-0.1.0.dist-info/top_level.txt
lumberjax-0.1.0.dist-info/RECORD
