Metadata-Version: 2.1
Name: lumberjax
Version: 0.1.0
Summary: A JAX-based library for nothr.
Home-page: https://github.com/ltiao/lumberjax
Author: Louis Tiao
Author-email: louistiao@gmail.com
License: Apache Software License 2.0
Keywords: lumberjax
Platform: UNKNOWN
Classifier: Development Status :: 2 - Pre-Alpha
Classifier: Intended Audience :: Developers
Classifier: License :: OSI Approved :: Apache Software License
Classifier: Natural Language :: English
Classifier: Programming Language :: Python :: 3
Classifier: Programming Language :: Python :: 3.6
Classifier: Programming Language :: Python :: 3.7
Classifier: Programming Language :: Python :: 3.8
Requires-Python: >=3.6
Requires-Dist: Click (>=7.0)
